{
  "bds": {
    "name": "visualanalytics",
    "id": "visualanalytics",
    "platform": [
      "desktop",
      "mobile"
    ],
    "author": "CMT",
    "summary": null,
    "license": "BSD",
    "version": "1.0.1",
    "pages": [
      {
        "visualanalytics": {
          "hotspots": [
            {
              "type": "input",
              "id": "txtInput",
              "options": [
                "mandatory",
                "enabled"
              ]
            },
            {
              "type": "input",
              "id": "btnShowHide",
              "options": [
                "mandatory",
                "enabled"
              ]
            },
            {
              "type": "output",
              "id": "txtSaved",
              "options": [
              ]
            },
            {
              "type": "navigation",
              "id": "btnExample",
              "options": [
                "target",
                "navigationTransition",
                "navigationType",
                "enabled"
              ]
            }
          ]
        }
      }
    ]
  }
}